matricula_online_scraper/__init__.py
matricula_online_scraper/__main__.py
matricula_online_scraper/logging_config.py
matricula_online_scraper/main.py
matricula_online_scraper/cli/__init__.py
matricula_online_scraper/cli/newsfeed.py
matricula_online_scraper/cli/parish.py
matricula_online_scraper/pipelines/images_pipeline.py
matricula_online_scraper/spiders/__init__.py
matricula_online_scraper/spiders/church_register.py
matricula_online_scraper/spiders/newsfeed_spider.py
matricula_online_scraper/spiders/parish.py
matricula_online_scraper/spiders/parish_list.py
matricula_online_scraper/spiders/utils.py
matricula_online_scraper/utils/file_format.py
matricula_online_scraper/utils/matricula_datestring.py
matricula_online_scraper/utils/matricula_pagination.py
matricula_online_scraper/utils/matricula_url.py
matricula_online_scraper-0.7.2.dist-info/METADATA
matricula_online_scraper-0.7.2.dist-info/WHEEL
matricula_online_scraper-0.7.2.dist-info/entry_points.txt
matricula_online_scraper-0.7.2.dist-info/licenses/LICENSE
matricula_online_scraper-0.7.2.dist-info/RECORD
