Metadata-Version: 2.4
Name: matricula-online-scraper
Version: 0.7.2
Summary: Command Line Interface tool for scraping Matricula Online https://data.matricula-online.eu.
Project-URL: repository, https://github.com/lsg551/matricula-online-scraper
Author-email: Luis Schulte <git@luisschulte.com>
License: MIT
License-File: LICENSE
Keywords: matricula,matricula-online,parish-registers,scraper
Classifier: Development Status :: 4 - Beta
Classifier: Environment :: Console
Classifier: Framework :: Scrapy
Classifier: License :: OSI Approved :: MIT License
Classifier: Programming Language :: Python :: 3.12
Classifier: Programming Language :: Python :: 3.13
Requires-Python: >=3.12
Requires-Dist: pillow>=11.1.0
Requires-Dist: scrapy<3.0.0,>=2.11.1
Requires-Dist: typer<1.0.0,>=0.15
